neuro_tagger
